keystoneauth_oidc/__init__.py
keystoneauth_oidc/exceptions.py
keystoneauth_oidc/loading.py
keystoneauth_oidc/plugin.py
keystoneauth_oidc/tests/__init__.py
keystoneauth_oidc/tests/unit/__init__.py
keystoneauth_oidc/tests/unit/test_loading.py
keystoneauth_oidc/tests/unit/test_oidc.py
keystoneauth_oidc-1.0.0.dist-info/AUTHORS
keystoneauth_oidc-1.0.0.dist-info/LICENSE
keystoneauth_oidc-1.0.0.dist-info/METADATA
keystoneauth_oidc-1.0.0.dist-info/WHEEL
keystoneauth_oidc-1.0.0.dist-info/entry_points.txt
keystoneauth_oidc-1.0.0.dist-info/pbr.json
keystoneauth_oidc-1.0.0.dist-info/top_level.txt
keystoneauth_oidc-1.0.0.dist-info/RECORD
