Metadata-Version: 2.1
Name: keystoneauth-oidc
Version: 1.0.0
Summary: OpenID Connect support for OpenStack keystoneauth library
Home-page: https://github.com/IFCA/keystoneauth-oidc
Author: Alvaro Lopez Garcia
Author-email: aloga@ifca.unican.es
License: UNKNOWN
Platform: UNKNOWN
Classifier: Environment :: OpenStack
Classifier: Intended Audience :: Information Technology
Classifier: Intended Audience :: System Administrators
Classifier: License :: OSI Approved :: Apache Software License
Classifier: Operating System :: POSIX :: Linux
Classifier: Programming Language :: Python
Classifier: Programming Language :: Python :: Implementation :: CPython
Classifier: Programming Language :: Python :: 3 :: Only
Classifier: Programming Language :: Python :: 3
Classifier: Programming Language :: Python :: 3.6
Classifier: Programming Language :: Python :: 3.7
Classifier: Programming Language :: Python :: 3.8
Requires-Python: >=3.6
Requires-Dist: keystoneauth1 (>=2.10.0)
Requires-Dist: pbr (!=2.1.0,>=2.0.0)
Requires-Dist: positional (>=1.1.1)
Requires-Dist: six (>=1.10.0)
